Workbook

Sheet Raw
B2: Order ID | C2: Date | D2: Product | E2: Price | F2: Quantity | G2: Purchase Type | H2: Payment Method | I2: Manager | J2: City
B3: 10452 | C3: 44872 | D3: Fries | E3: 3.49 | F3: 573.0659 | G3: Online | H3: Gift Card | I3: Tom Jackson | J3: London
B4: 10453 | C4: 44872 | D4: Beverages | E4: 2.95 | F4: 745.76271 | G4: Online | H4: Gift Card | I4: Pablo Perez | J4: Madrid
B5: 10454 | C5: 44872 | D5: Sides & Other | E5: 4.99 | F5: 200.4008 | G5: In-store | H5: Gift Card | I5: Joao Silva | J5: Lisbon
B6: 10455 | C6: 44873 | D6: Burgers | E6: 12.99 | F6: 569.66898 | G6: In-store | H6: Credit Card | I6: Walter Muller | J6: Berlin
B7: 10456 | C7: 44873 | D7: Chicken Sandwiches | E7: 9.95 | F7: 201.00503 | G7: In-store | H7: Credit Card | I7: Walter Muller | J7: Berlin
B8: 10457 | C8: 44873 | D8: Fries | E8: 3.49 | F8: 573.0659 | G8: In-store | H8: Credit Card | I8: Remy Monet | J8: Paris
B9: 10457 | C9: 44873 | D9: Fries | E9: 3.49 | F9: 573.0659 | G9: In-store | H9: Credit Card | I9: Remy Monet | J9: Paris
B10: 10459 | C10: 44873 | D10: Sides & Other | E10: 4.99 | F10: 200.4008 | G10: In-store | H10: Credit Card | I10: Walter Muller | J10: Berlin
B11: 10460 | C11: 44874 | D11: Burgers | E11: 12.99 | F11: 554.27252 | G11: In-store | H11: Credit Card | I11: Remy Monet | J11: Paris
B12: 10461 | C12: 44874 | D12: Chicken Sandwiches | E12: 9.95 | F12: 201.00503 | G12: In-store | H12: Credit Card | I12: Remy Monet | J12: Paris
B13: 10462 | C13: 44874 | D13: Fries | E13: 3.49 | F13: 573.0659 | G13: In-store | H13: Credit Card | I13: Remy Monet | J13: Paris
B14: 10463 | C14: 44874 | D14: Beverages | E14: 2.95 | F14: 677.9661 | G14: In-store | H14: Credit Card | I14: Remy Monet | J14: Paris
... B264: 10713 | C264: 44924 | D264: Beverages | E264: 2.95 | F264: 677.9661 | G264: Drive-thru | H264: Gift Card | I264: Walter Muller | J264: Berlin

Sheet Raw (2)
B2: Order ID | C2: Date | D2: Product | E2: Price | F2: Purchase Type | G2: Payment Method | H2: Manager | I2: Quantity2 | J2: City | K2: Country/region | L2: Revenue
B3: 10452 | C3: 44872 | D3: Fries | E3: 3.49 | F3: Online | G3: Gift Card | H3: Tom Jackson | I3: 574 | J3: #VALUE! | K3: {=_FV(Table2[[#This Row],[City]],"Country/region",TRUE)} -> #VALUE! | L3: =Table2[[#This Row],[Quantity2]]*Table2[[#This Row],[Price]] -> 2003.26
B4: 10453 | C4: 44872 | D4: Beverages | E4: 2.95 | F4: Online | G4: Gift Card | H4: Pablo Perez | I4: 746 | J4: #VALUE! | K4: {=_FV(Table2[[#This Row],[City]],"Country/region",TRUE)} -> #VALUE! | L4: =Table2[[#This Row],[Quantity2]]*Table2[[#This Row],[Price]] -> 2200.7
B5: 10454 | C5: 44872 | D5: Sides & Other | E5: 4.99 | F5: In-store | G5: Gift Card | H5: Joao Silva | I5: 201 | J5: #VALUE! | K5: {=_FV(Table2[[#This Row],[City]],"Country/region",TRUE)} -> #VALUE! | L5: =Table2[[#This Row],[Quantity2]]*Table2[[#This Row],[Price]] -> 1002.99 | N5: Price | Q5: Quantity
B6: 10455 | C6: 44873 | D6: Burgers | E6: 12.99 | F6: In-store | G6: Credit Card | H6: Walter Muller | I6: 570 | J6: #VALUE! | K6: {=_FV(Table2[[#This Row],[City]],"Country/region",TRUE)} -> #VALUE! | L6: =Table2[[#This Row],[Quantity2]]*Table2[[#This Row],[Price]] -> 7404.3
B7: 10456 | C7: 44873 | D7: Chicken Sandwiches | E7: 9.95 | F7: In-store | G7: Credit Card | H7: Walter Muller | I7: 202 | J7: #VALUE! | K7: {=_FV(Table2[[#This Row],[City]],"Country/region",TRUE)} -> #VALUE! | L7: =Table2[[#This Row],[Quantity2]]*Table2[[#This Row],[Price]] -> 2009.9 | N7: Mean | O7: 7.3410117 | Q7: Mean | R7: 461.24125
B8: 10457 | C8: 44873 | D8: Fries | E8: 3.49 | F8: In-store | G8: Credit Card | H8: Remy Monet | I8: 574 | J8: #VALUE! | K8: {=_FV(Table2[[#This Row],[City]],"Country/region",TRUE)} -> #VALUE! | L8: =Table2[[#This Row],[Quantity2]]*Table2[[#This Row],[Price]] -> 2003.26 | N8: Standard Error | O8: 0.30396506 | Q8: Standard Error | R8: 13.380974
B9: 10459 | C9: 44873 | D9: Sides & Other | E9: 4.99 | F9: In-store | G9: Credit Card | H9: Walter Muller | I9: 201 | J9: #VALUE! | K9: {=_FV(Table2[[#This Row],[City]],"Country/region",TRUE)} -> #VALUE! | L9: =Table2[[#This Row],[Quantity2]]*Table2[[#This Row],[Price]] -> 1002.99 | N9: Median | O9: 4.99 | Q9: Median | R9: 539
B10: 10460 | C10: 44874 | D10: Burgers | E10: 12.99 | F10: In-store | G10: Credit Card | H10: Remy Monet | I10: 555 | J10: #VALUE! | K10: {=_FV(Table2[[#This Row],[City]],"Country/region",TRUE)} -> #VALUE! | L10: =Table2[[#This Row],[Quantity2]]*Table2[[#This Row],[Price]] -> 7209.45 | N10: Mode | O10: 12.99 | Q10: Mode | R10: 201
B11: 10461 | C11: 44874 | D11: Chicken Sandwiches | E11: 9.95 | F11: In-store | G11: Credit Card | H11: Remy Monet | I11: 202 | J11: #VALUE! | K11: {=_FV(Table2[[#This Row],[City]],"Country/region",TRUE)} -> #VALUE! | L11: =Table2[[#This Row],[Quantity2]]*Table2[[#This Row],[Price]] -> 2009.9 | N11: Standard Deviation | O11: 4.8729306 | Q11: Standard Deviation | R11: 214.51334
B12: 10462 | C12: 44874 | D12: Fries | E12: 3.49 | F12: In-store | G12: Credit Card | H12: Remy Monet | I12: 574 | J12: #VALUE! | K12: {=_FV(Table2[[#This Row],[City]],"Country/region",TRUE)} -> #VALUE! | L12: =Table2[[#This Row],[Quantity2]]*Table2[[#This Row],[Price]] -> 2003.26 | N12: Sample Variance | O12: 23.745453 | Q12: Sample Variance | R12: 46015.973
B13: 10463 | C13: 44874 | D13: Beverages | E13: 2.95 | F13: In-store | G13: Credit Card | H13: Remy Monet | I13: 678 | J13: #VALUE! | K13: {=_FV(Table2[[#This Row],[City]],"Country/region",TRUE)} -> #VALUE! | L13: =Table2[[#This Row],[Quantity2]]*Table2[[#This Row],[Price]] -> 2000.1 | N13: Kurtosis | O13: 4.6742476 | Q13: Kurtosis | R13: -1.7242037
B14: 10464 | C14: 44874 | D14: Sides & Other | E14: 4.99 | F14: In-store | G14: Credit Card | H14: Remy Monet | I14: 201 | J14: #VALUE! | K14: {=_FV(Table2[[#This Row],[City]],"Country/region",TRUE)} -> #VALUE! | L14: =Table2[[#This Row],[Quantity2]]*Table2[[#This Row],[Price]] -> 1002.99 | N14: Skewness | O14: 1.6233289 | Q14: Skewness | R14: -0.2142499
B15: 10465 | C15: 44875 | D15: Burgers | E15: 12.99 | F15: In-store | G15: Credit Card | H15: Pablo Perez | I15: 555 | J15: #VALUE! | K15: {=_FV(Table2[[#This Row],[City]],"Country/region",TRUE)} -> #VALUE! | L15: =Table2[[#This Row],[Quantity2]]*Table2[[#This Row],[Price]] -> 7209.45 | N15: Range | O15: 30.27 | Q15: Range | R15: 554
B16: 10466 | C16: 44875 | D16: Chicken Sandwiches | E16: 9.95 | F16: In-store | G16: Credit Card | H16: Pablo Perez | I16: 202 | J16: #VALUE! | K16: {=_FV(Table2[[#This Row],[City]],"Country/region",TRUE)} -> #VALUE! | L16: =Table2[[#This Row],[Quantity2]]*Table2[[#This Row],[Price]] -> 2009.9 | N16: Minimum | O16: 2.95 | Q16: Minimum | R16: 201
B17: 10467 | C17: 44875 | D17: Fries | E17: 3.49 | F17: In-store | G17: Credit Card | H17: Pablo Perez | I17: 574 | J17: #VALUE! | K17: {=_FV(Table2[[#This Row],[City]],"Country/region",TRUE)} -> #VALUE! | L17: =Table2[[#This Row],[Quantity2]]*Table2[[#This Row],[Price]] -> 2003.26 | N17: Maximum | O17: 33.22 | Q17: Maximum | R17: 755
B18: 10468 | C18: 44875 | D18: Beverages | E18: 2.95 | F18: In-store | G18: Credit Card | H18: Pablo Perez | I18: 678 | J18: #VALUE! | K18: {=_FV(Table2[[#This Row],[City]],"Country/region",TRUE)} -> #VALUE! | L18: =Table2[[#This Row],[Quantity2]]*Table2[[#This Row],[Price]] -> 2000.1 | N18: Sum | O18: 1886.64 | Q18: Sum | R18: 118539
B19: 10470 | C19: 44876 | D19: Burgers | E19: 12.99 | F19: In-store | G19: Credit Card | H19: Pablo Perez | I19: 555 | J19: #VALUE! | K19: {=_FV(Table2[[#This Row],[City]],"Country/region",TRUE)} -> #VALUE! | L19: =Table2[[#This Row],[Quantity2]]*Table2[[#This Row],[Price]] -> 7209.45 | N19: Count | O19: 257 | Q19: Count | R19: 257
B20: 10471 | C20: 44876 | D20: Chicken Sandwiches | E20: 9.95 | F20: In-store | G20: Credit Card | H20: Pablo Perez | I20: 202 | J20: #VALUE! | K20: {=_FV(Table2[[#This Row],[City]],"Country/region",TRUE)} -> #VALUE! | L20: =Table2[[#This Row],[Quantity2]]*Table2[[#This Row],[Price]] -> 2009.9
B21: 10472 | C21: 44876 | D21: Fries | E21: 3.49 | F21: In-store | G21: Credit Card | H21: Pablo Perez | I21: 631 | J21: #VALUE! | K21: {=_FV(Table2[[#This Row],[City]],"Country/region",TRUE)} -> #VALUE! | L21: =Table2[[#This Row],[Quantity2]]*Table2[[#This Row],[Price]] -> 2202.19
B22: 10473 | C22: 44876 | D22: Beverages | E22: 2.95 | F22: In-store | G22: Credit Card | H22: Pablo Perez | I22: 678 | J22: #VALUE! | K22: {=_FV(Table2[[#This Row],[City]],"Country/region",TRUE)} -> #VALUE! | L22: =Table2[[#This Row],[Quantity2]]*Table2[[#This Row],[Price]] -> 2000.1
B23: 10474 | C23: 44876 | D23: Sides & Other | E23: 4.99 | F23: In-store | G23: Credit Card | H23: Pablo Perez | I23: 201 | J23: #VALUE! | K23: {=_FV(Table2[[#This Row],[City]],"Country/region",TRUE)} -> #VALUE! | L23: =Table2[[#This Row],[Quantity2]]*Table2[[#This Row],[Price]] -> 1002.99
B24: 10475 | C24: 44877 | D24: Burgers | E24: 12.99 | F24: In-store | G24: Credit Card | H24: Pablo Perez | I24: 524 | J24: #VALUE! | K24: {=_FV(Table2[[#This Row],[City]],"Country/region",TRUE)} -> #VALUE! | L24: =Table2[[#This Row],[Quantity2]]*Table2[[#This Row],[Price]] -> 6806.76
B25: 10476 | C25: 44877 | D25: Chicken Sandwiches | E25: 9.95 | F25: In-store | G25: Credit Card | H25: Pablo Perez | I25: 202 | J25: #VALUE! | K25: {=_FV(Table2[[#This Row],[City]],"Country/region",TRUE)} -> #VALUE! | L25: =Table2[[#This Row],[Quantity2]]*Table2[[#This Row],[Price]] -> 2009.9
B26: 10477 | C26: 44877 | D26: Fries | E26: 3.49 | F26: In-store | G26: Credit Card | H26: Pablo Perez | I26: 631 | J26: #VALUE! | K26: {=_FV(Table2[[#This Row],[City]],"Country/region",TRUE)} -> #VALUE! | L26: =Table2[[#This Row],[Quantity2]]*Table2[[#This Row],[Price]] -> 2202.19
B27: 10478 | C27: 44877 | D27: Beverages | E27: 2.95 | F27: In-store | G27: Credit Card | H27: Pablo Perez | I27: 678 | J27: #VALUE! | K27: {=_FV(Table2[[#This Row],[City]],"Country/region",TRUE)} -> #VALUE! | L27: =Table2[[#This Row],[Quantity2]]*Table2[[#This Row],[Price]] -> 2000.1
B28: 10479 | C28: 44877 | D28: Sides & Other | E28: 4.99 | F28: In-store | G28: Credit Card | H28: Pablo Perez | I28: 201 | J28: #VALUE! | K28: {=_FV(Table2[[#This Row],[City]],"Country/region",TRUE)} -> #VALUE! | L28: =Table2[[#This Row],[Quantity2]]*Table2[[#This Row],[Price]] -> 1002.99
B29: 10480 | C29: 44878 | D29: Burgers | E29: 12.99 | F29: In-store | G29: Credit Card | H29: Pablo Perez | I29: 509 | J29: #VALUE! | K29: {=_FV(Table2[[#This Row],[City]],"Country/region",TRUE)} -> #VALUE! | L29: =Table2[[#This Row],[Quantity2]]*Table2[[#This Row],[Price]] -> 6611.91
B30: 10481 | C30: 44878 | D30: Chicken Sandwiches | E30: 9.95 | F30: In-store | G30: Credit Card | H30: Pablo Perez | I30: 202 | J30: #VALUE! | K30: {=_FV(Table2[[#This Row],[City]],"Country/region",TRUE)} -> #VALUE! | L30: =Table2[[#This Row],[Quantity2]]*Table2[[#This Row],[Price]] -> 2009.9
B31: 10482 | C31: 44878 | D31: Fries | E31: 25.5 | F31: In-store | G31: Credit Card | H31: Joao Silva | I31: 631 | J31: #VALUE! | K31: {=_FV(Table2[[#This Row],[City]],"Country/region",TRUE)} -> #VALUE! | L31: =Table2[[#This Row],[Quantity2]]*Table2[[#This Row],[Price]] -> 16090.5
... B259: 10713 | C259: 44924 | D259: Beverages | E259: 2.95 | F259: Drive-thru | G259: Gift Card | H259: Walter Muller | I259: 678 | J259: #VALUE! | K259: {=_FV(Table2[[#This Row],[City]],"Country/region",TRUE)} -> #VALUE! | L259: =Table2[[#This Row],[Quantity2]]*Table2[[#This Row],[Price]] -> 2000.1

Sheet Clean
B2: Order ID | C2: Date | D2: Product | E2: Price | F2: Quantity | G2: Cost | H2: City | I2: Country | J2: Purchase Type | K2: Payment Method | L2: Manager | M2: Revenue
B3: 10452 | C3: 44872 | D3: Fries | E3: 3.49 | F3: 574 | G3: 0.88 | H3: #VALUE! | I3: {=_FV(H3,"Country/region",TRUE)} -> #VALUE! | J3: Online | K3: Gift Card | L3: Tom Jackson | M3: =Table1[[#This Row],[Price]]*Table1[[#This Row],[Quantity]] -> 2003.26
B4: 10453 | C4: 44872 | D4: Beverages | E4: 2.95 | F4: 746 | G4: 0.47 | H4: #VALUE! | I4: {=_FV(H4,"Country/region",TRUE)} -> #VALUE! | J4: Online | K4: Gift Card | L4: Pablo Perez | M4: =Table1[[#This Row],[Price]]*Table1[[#This Row],[Quantity]] -> 2200.7
B5: 10454 | C5: 44872 | D5: Sides & Other | E5: 4.99 | F5: 201 | G5: 2.25 | H5: #VALUE! | I5: {=_FV(H5,"Country/region",TRUE)} -> #VALUE! | J5: In-store | K5: Gift Card | L5: Joao Silva | M5: =Table1[[#This Row],[Price]]*Table1[[#This Row],[Quantity]] -> 1002.99
B6: 10455 | C6: 44873 | D6: Burgers | E6: 12.99 | F6: 570 | G6: 4.32 | H6: #VALUE! | I6: {=_FV(H6,"Country/region",TRUE)} -> #VALUE! | J6: In-store | K6: Credit Card | L6: Walter Muller | M6: =Table1[[#This Row],[Price]]*Table1[[#This Row],[Quantity]] -> 7404.3
B7: 10456 | C7: 44873 | D7: Chicken Sandwiches | E7: 9.95 | F7: 202 | G7: 2.85 | H7: #VALUE! | I7: {=_FV(H7,"Country/region",TRUE)} -> #VALUE! | J7: In-store | K7: Credit Card | L7: Walter Muller | M7: =Table1[[#This Row],[Price]]*Table1[[#This Row],[Quantity]] -> 2009.9
B8: 10457 | C8: 44873 | D8: Fries | E8: 3.49 | F8: 574 | G8: 0.88 | H8: #VALUE! | I8: {=_FV(H8,"Country/region",TRUE)} -> #VALUE! | J8: In-store | K8: Credit Card | L8: Remy Monet | M8: =Table1[[#This Row],[Price]]*Table1[[#This Row],[Quantity]] -> 2003.26
B9: 10459 | C9: 44873 | D9: Sides & Other | E9: 4.99 | F9: 201 | G9: 2.25 | H9: #VALUE! | I9: {=_FV(H9,"Country/region",TRUE)} -> #VALUE! | J9: In-store | K9: Credit Card | L9: Remy Monet | M9: =Table1[[#This Row],[Price]]*Table1[[#This Row],[Quantity]] -> 1002.99
B10: 10460 | C10: 44874 | D10: Burgers | E10: 12.99 | F10: 555 | G10: 4.32 | H10: #VALUE! | I10: {=_FV(H10,"Country/region",TRUE)} -> #VALUE! | J10: In-store | K10: Credit Card | L10: Walter Muller | M10: =Table1[[#This Row],[Price]]*Table1[[#This Row],[Quantity]] -> 7209.45
B11: 10461 | C11: 44874 | D11: Chicken Sandwiches | E11: 9.95 | F11: 202 | G11: 2.85 | H11: #VALUE! | I11: {=_FV(H11,"Country/region",TRUE)} -> #VALUE! | J11: In-store | K11: Credit Card | L11: Remy Monet | M11: =Table1[[#This Row],[Price]]*Table1[[#This Row],[Quantity]] -> 2009.9
B12: 10462 | C12: 44874 | D12: Fries | E12: 3.49 | F12: 574 | G12: 0.88 | H12: #VALUE! | I12: {=_FV(H12,"Country/region",TRUE)} -> #VALUE! | J12: In-store | K12: Credit Card | L12: Remy Monet | M12: =Table1[[#This Row],[Price]]*Table1[[#This Row],[Quantity]] -> 2003.26
B13: 10463 | C13: 44874 | D13: Beverages | E13: 2.95 | F13: 678 | G13: 0.47 | H13: #VALUE! | I13: {=_FV(H13,"Country/region",TRUE)} -> #VALUE! | J13: In-store | K13: Credit Card | L13: Remy Monet | M13: =Table1[[#This Row],[Price]]*Table1[[#This Row],[Quantity]] -> 2000.1
B14: 10464 | C14: 44874 | D14: Sides & Other | E14: 4.99 | F14: 201 | G14: 2.25 | H14: #VALUE! | I14: {=_FV(H14,"Country/region",TRUE)} -> #VALUE! | J14: In-store | K14: Credit Card | L14: Remy Monet | M14: =Table1[[#This Row],[Price]]*Table1[[#This Row],[Quantity]] -> 1002.99
... B256: 10713 | C256: 44924 | D256: Beverages | E256: 2.95 | F256: 678 | G256: 0.47 | H256: #VALUE! | I256: {=_FV(H256,"Country/region",TRUE)} -> #VALUE! | J256: Drive-thru | K256: Gift Card | L256: Walter Muller | M256: =Table1[[#This Row],[Price]]*Table1[[#This Row],[Quantity]] -> 2000.1

Sheet Analysis
B2: Data Analysis Questions | H2: Row Labels | I2: Sum of Quantity2 | K2: Sum of Revenue
H3: Beverages | I3: 35666 | K3: 812135.13
B4: 1) What is our best selling product? | H4: Fries | I4: 32067
B5: Beverages | H5: Burgers | I5: 29572 | K5: Row Labels | L5: Sum of Revenue
B6: 2) What is our total revenue? | H6: Chicken Sandwiches | I6: 11184 | K6: Cash | L6: 0.29489446
B7: 812135.13 | H7: Sides & Other | I7: 10050 | K7: Credit Card | L7: 0.49722372
B8: 3) What is the revenue breakdown by payment method? | H8: Grand Total | I8: 118539 | K8: Gift Card | L8: 0.20788182
B9: Credit Card is major payment option | K9: Grand Total | L9: 1

Sheet Findings
B2: Select Manager -> | C2: Pablo Perez | J2: Tom Jackson
J3: Pablo Perez
B4: Geography | J4: Joao Silva
B5: Country | C5: =_xlfn.XLOOKUP(C2,Table1[Manager],Table1[Country]) -> #VALUE! | J5: Walter Muller
B6: City | C6: =_xlfn.XLOOKUP(C2,Table1[Manager],Table1[City]) -> #VALUE! | J6: Remy Monet
B8: Revenue
B9: Fries | C9: =SUMIFS(Table1[Revenue],Table1[Product],Findings!B9,Table1[Manager],Findings!$C$2) -> 17219.66
B10: Beverages | C10: =SUMIFS(Table1[Revenue],Table1[Product],Findings!B10,Table1[Manager],Findings!$C$2) -> 18402.1
B11: Sides & Other | C11: =SUMIFS(Table1[Revenue],Table1[Product],Findings!B11,Table1[Manager],Findings!$C$2) -> 9026.91
B12: Burgers | C12: =SUMIFS(Table1[Revenue],Table1[Product],Findings!B12,Table1[Manager],Findings!$C$2) -> 73692.27
B13: Chicken Sandwiches | C13: =SUMIFS(Table1[Revenue],Table1[Product],Findings!B13,Table1[Manager],Findings!$C$2) -> 18089.1
B14: Total | C14: =SUM(C9:C13) -> 136430.04
